arorm/__init__.py
arorm/store.py
arorm-0.3.3.dist-info/LICENCE
arorm-0.3.3.dist-info/METADATA
arorm-0.3.3.dist-info/WHEEL
arorm-0.3.3.dist-info/top_level.txt
arorm-0.3.3.dist-info/RECORD
