Metadata-Version: 2.1
Name: arorm
Version: 0.3.3
Summary: A python orm with identity pattern mainly for arango
Home-page: https://github.com/patricklx/ar-orm
Author: Patrick Pircher
Author-email: 
License: MIT
License-File: LICENCE
Requires-Dist: event-emitter
Requires-Dist: inflection
Requires-Dist: arango
Requires-Dist: arango-orm
